nu/__init__.py
xni-0.1.0.dist-info/METADATA
xni-0.1.0.dist-info/WHEEL
xni-0.1.0.dist-info/top_level.txt
xni-0.1.0.dist-info/RECORD
