Metadata-Version: 2.4
Name: xni
Version: 0.1.0
Summary: A minimal Python package
Author-email: Yury Selivanov <yselivanov@gmail.com>
License: MIT
Project-URL: Homepage, https://github.com/1st1
Classifier: Development Status :: 3 - Alpha
Classifier: Intended Audience :: Developers
Classifier: License :: OSI Approved :: MIT License
Classifier: Programming Language :: Python :: 3
Classifier: Programming Language :: Python :: 3.7
Classifier: Programming Language :: Python :: 3.8
Classifier: Programming Language :: Python :: 3.9
Classifier: Programming Language :: Python :: 3.10
Classifier: Programming Language :: Python :: 3.11
Classifier: Programming Language :: Python :: 3.12
Requires-Python: >=3.7
